{"students": {"Faisal": {"Ziyad": 3, "Salman": 2, "Fahad": 2, "Naif": 2, "Firas": 3, "Alaa": 3, "Dania": 2, "Hatoon": 0, "Wadia": 0, "Raghad": 3, "Osama": 1, "Sarraa": 1, "Ashwag": 1, "Ahmad": 2, "Mosaab": 3, "Abdulaziz": 2, "Samer": 2, "Ali": 3, "Mousa": 0, "Mohammed": 0, "Abduallah": 5, "Hamad": 1, "Majed": 2}, "Ziyad": {"Faisal": 3, "Salman": 1, "Fahad": 4, "Naif": 1, "Firas": 2, "Alaa": 4, "Dania": 2, "Hatoon": 1, "Wadia": 1, "Raghad": 0, "Osama": 4, "Sarraa": 2, "Ashwag": 1, "Ahmad": 4, "Mosaab": 1, "Abdulaziz": 2, "Samer": 3, "Ali": 1, "Mousa": 1, "Mohammed": 1, "Abduallah": 1, "Hamad": 3, "Majed": 1}, "Salman": {"Faisal": 2, "Ziyad": 1, "Fahad": 0, "Naif": 5, "Firas": 2, "Alaa": 0, "Dania": 4, "Hatoon": 2, "Wadia": 2, "Raghad": 3, "Osama": 0, "Sarraa": 2, "Ashwag": 3, "Ahmad": 0, "Mosaab": 3, "Abdulaziz": 3, "Samer": 1, "Ali": 1, "Mousa": 3, "Mohammed": 2, "Abduallah": 3, "Hamad": 1, "Majed": 1}, "Fahad": {"Faisal": 2, "Ziyad": 4, "Salman": 0, "Naif": 0, "Firas": 3, "Alaa": 2, "Dania": 0, "Hatoon": 3, "Wadia": 1, "Raghad": 1, "Osama": 4, "Sarraa": 1, "Ashwag": 1, "Ahmad": 4, "Mosaab": 0, "Abdulaziz": 1, "Samer": 2, "Ali": 2, "Mousa": 2, "Mohammed": 1, "Abduallah": 3, "Hamad": 3, "Majed": 2}, "Naif": {"Faisal": 2, "Ziyad": 1, "Salman": 5, "Fahad": 0, "Firas": 1, "Alaa": 2, "Dania": 4, "Hatoon": 1, "Wadia": 2, "Raghad": 2, "Osama": 1, "Sarraa": 3, "Ashwag": 3, "Ahmad": 1, "Mosaab": 2, "Abdulaziz": 2, "Samer": 1, "Ali": 2, "Mousa": 1, "Mohammed": 2, "Abduallah": 4, "Hamad": 1, "Majed": 1}, "Firas": {"Faisal": 3, "Ziyad": 2, "Salman": 2, "Fahad": 3, "Naif": 1, "Alaa": 3, "Dania": 1, "Hatoon": 2, "Wadia": 1, "Raghad": 2, "Osama": 2, "Sarraa": 1, "Ashwag": 1, "Ahmad": 2, "Mosaab": 0, "Abdulaziz": 1, "Samer": 2, "Ali": 2, "Mousa": 3, "Mohammed": 1, "Abduallah": 3, "Hamad": 3, "Majed": 2}, "Alaa": {"Faisal": 3, "Ziyad": 4, "Salman": 0, "Fahad": 2, "Naif": 2, "Firas": 3, "Dania": 2, "Hatoon": 2, "Wadia": 3, "Raghad": 0, "Osama": 2, "Sarraa": 1, "Ashwag": 1, "Ahmad": 3, "Mosaab": 1, "Abdulaziz": 2, "Samer": 2, "Ali": 3, "Mousa": 2, "Mohammed": 1, "Abduallah": 1, "Hamad": 2, "Majed": 1}, "Dania": {"Faisal": 2, "Ziyad": 2, "Salman": 4, "Fahad": 0, "Naif": 4, "Firas": 1, "Alaa": 2, "Hatoon": 2, "Wadia": 2, "Raghad": 3, "Osama": 0, "Sarraa": 2, "Ashwag": 2, "Ahmad": 0, "Mosaab": 3, "Abdulaziz": 3, "Samer": 1, "Ali": 2, "Mousa": 1, "Mohammed": 2, "Abduallah": 1, "Hamad": 3, "Majed": 1}, "Hatoon": {"Faisal": 0, "Ziyad": 1, "Salman": 2, "Fahad": 3, "Naif": 1, "Firas": 2, "Alaa": 2, "Dania": 2, "Wadia": 4, "Raghad": 5, "Osama": 1, "Sarraa": 2, "Ashwag": 1, "Ahmad": 1, "Mosaab": 2, "Abdulaziz": 1, "Samer": 1, "Ali": 2, "Mousa": 4, "Mohammed": 4, "Abduallah": 0, "Hamad": 3, "Majed": 0}, "Wadia": {"Faisal": 0, "Ziyad": 1, "Salman": 2, "Fahad": 1, "Naif": 2, "Firas": 1, "Alaa": 3, "Dania": 2, "Hatoon": 4, "Raghad": 1, "Osama": 2, "Sarraa": 2, "Ashwag": 1, "Ahmad": 3, "Mosaab": 2, "Abdulaziz": 1, "Samer": 3, "Ali": 1, "Mousa": 3, "Mohammed": 5, "Abduallah": 1, "Hamad": 1, "Majed": 1}, "Raghad": {"Faisal": 3, "Ziyad": 0, "Salman": 3, "Fahad": 1, "Naif": 2, "Firas": 2, "Alaa": 0, "Dania": 3, "Hatoon": 5, "Wadia": 1, "Osama": 0, "Sarraa": 3, "Ashwag": 3, "Ahmad": 0, "Mosaab": 5, "Abdulaziz": 2, "Samer": 0, "Ali": 2, "Mousa": 2, "Mohammed": 2, "Abduallah": 2, "Hamad": 2, "Majed": 1}, "Osama": {"Faisal": 1, "Ziyad": 4, "Salman": 0, "Fahad": 4, "Naif": 1, "Firas": 2, "Alaa": 2, "Dania": 0, "Hatoon": 1, "Wadia": 2, "Raghad": 0, "Sarraa": 3, "Ashwag": 3, "Ahmad": 3, "Mosaab": 0, "Abdulaziz": 0, "Samer": 2, "Ali": 2, "Mousa": 2, "Mohammed": 3, "Abduallah": 2, "Hamad": 3, "Majed": 4}, "Sarraa": {"Faisal": 1, "Ziyad": 2, "Salman": 2, "Fahad": 1, "Naif": 3, "Firas": 1, "Alaa": 1, "Dania": 2, "Hatoon": 2, "Wadia": 2, "Raghad": 3, "Osama": 3, "Ashwag": 4, "Ahmad": 1, "Mosaab": 2, "Abdulaziz": 3, "Samer": 2, "Ali": 2, "Mousa": 1, "Mohammed": 2, "Abduallah": 1, "Hamad": 1, "Majed": 2}, "Ashwag": {"Faisal": 1, "Ziyad": 1, "Salman": 3, "Fahad": 1, "Naif": 3, "Firas": 1, "Alaa": 1, "Dania": 2, "Hatoon": 1, "Wadia": 1, "Raghad": 3, "Osama": 3, "Sarraa": 4, "Ahmad": 0, "Mosaab": 4, "Abdulaziz": 2, "Samer": 1, "Ali": 2, "Mousa": 3, "Mohammed": 3, "Abduallah": 1, "Hamad": 0, "Majed": 3}, "Ahmad": {"Faisal": 2, "Ziyad": 4, "Salman": 0, "Fahad": 4, "Naif": 1, "Firas": 2, "Alaa": 3, "Dania": 0, "Hatoon": 1, "Wadia": 3, "Raghad": 0, "Osama": 3, "Sarraa": 1, "Ashwag": 0, "Mosaab": 2, "Abdulaziz": 1, "Samer": 6, "Ali": 2, "Mousa": 1, "Mohammed": 1, "Abduallah": 2, "Hamad": 3, "Majed": 1}, "Mosaab": {"Faisal": 3, "Ziyad": 1, "Salman": 3, "Fahad": 0, "Naif": 2, "Firas": 0, "Alaa": 1, "Dania": 3, "Hatoon": 2, "Wadia": 2, "Raghad": 5, "Osama": 0, "Sarraa": 2, "Ashwag": 4, "Ahmad": 2, "Abdulaziz": 2, "Samer": 2, "Ali": 1, "Mousa": 2, "Mohammed": 1, "Abduallah": 3, "Hamad": 1, "Majed": 1}, "Abdulaziz": {"Faisal": 2, "Ziyad": 2, "Salman": 3, "Fahad": 1, "Naif": 2, "Firas": 1, "Alaa": 2, "Dania": 3, "Hatoon": 1, "Wadia": 1, "Raghad": 2, "Osama": 0, "Sarraa": 3, "Ashwag": 2, "Ahmad": 1, "Mosaab": 2, "Samer": 1, "Ali": 3, "Mousa": 4, "Mohammed": 2, "Abduallah": 1, "Hamad": 0, "Majed": 2}, "Samer": {"Faisal": 2, "Ziyad": 3, "Salman": 1, "Fahad": 2, "Naif": 1, "Firas": 2, "Alaa": 2, "Dania": 1, "Hatoon": 1, "Wadia": 3, "Raghad": 0, "Osama": 2, "Sarraa": 2, "Ashwag": 1, "Ahmad": 6, "Mosaab": 2, "Abdulaziz": 1, "Ali": 4, "Mousa": 1, "Mohammed": 2, "Abduallah": 1, "Hamad": 2, "Majed": 1}, "Ali": {"Faisal": 3, "Ziyad": 1, "Salman": 1, "Fahad": 2, "Naif": 2, "Firas": 2, "Alaa": 3, "Dania": 2, "Hatoon": 2, "Wadia": 1, "Raghad": 2, "Osama": 2, "Sarraa": 2, "Ashwag": 2, "Ahmad": 2, "Mosaab": 1, "Abdulaziz": 3, "Samer": 4, "Mousa": 0, "Mohammed": 1, "Abduallah": 2, "Hamad": 1, "Majed": 2}, "Mousa": {"Faisal": 0, "Ziyad": 1, "Salman": 3, "Fahad": 2, "Naif": 1, "Firas": 3, "Alaa": 2, "Dania": 1, "Hatoon": 4, "Wadia": 3, "Raghad": 2, "Osama": 2, "Sarraa": 1, "Ashwag": 3, "Ahmad": 1, "Mosaab": 2, "Abdulaziz": 4, "Samer": 1, "Ali": 0, "Mohammed": 4, "Abduallah": 1, "Hamad": 1, "Majed": 1}, "Mohammed": {"Faisal": 0, "Ziyad": 1, "Salman": 2, "Fahad": 1, "Naif": 2, "Firas": 1, "Alaa": 1, "Dania": 2, "Hatoon": 4, "Wadia": 5, "Raghad": 2, "Osama": 3, "Sarraa": 2, "Ashwag": 3, "Ahmad": 1, "Mosaab": 1, "Abdulaziz": 2, "Samer": 2, "Ali": 1, "Mousa": 4, "Abduallah": 1, "Hamad": 1, "Majed": 1}, "Abduallah": {"Faisal": 5, "Ziyad": 1, "Salman": 3, "Fahad": 3, "Naif": 4, "Firas": 3, "Alaa": 1, "Dania": 1, "Hatoon": 0, "Wadia": 1, "Raghad": 2, "Osama": 2, "Sarraa": 1, "Ashwag": 1, "Ahmad": 2, "Mosaab": 3, "Abdulaziz": 1, "Samer": 1, "Ali": 2, "Mousa": 1, "Mohammed": 1, "Hamad": 2, "Majed": 2}, "Hamad": {"Faisal": 1, "Ziyad": 3, "Salman": 1, "Fahad": 3, "Naif": 1, "Firas": 3, "Alaa": 2, "Dania": 3, "Hatoon": 3, "Wadia": 1, "Raghad": 2, "Osama": 3, "Sarraa": 1, "Ashwag": 0, "Ahmad": 3, "Mosaab": 1, "Abdulaziz": 0, "Samer": 2, "Ali": 1, "Mousa": 1, "Mohammed": 1, "Abduallah": 2, "Majed": 2}, "Majed": {"Faisal": 2, "Ziyad": 1, "Salman": 1, "Fahad": 2, "Naif": 1, "Firas": 2, "Alaa": 1, "Dania": 1, "Hatoon": 0, "Wadia": 1, "Raghad": 1, "Osama": 4, "Sarraa": 2, "Ashwag": 3, "Ahmad": 1, "Mosaab": 1, "Abdulaziz": 2, "Samer": 1, "Ali": 2, "Mousa": 1, "Mohammed": 1, "Abduallah": 2, "Hamad": 2}}, "names": ["Faisal", "Ziyad", "Salman", "Fahad", "Naif", "Firas", "Alaa", "Dania", "Hatoon", "Wadia", "Raghad", "Osama", "Sarraa", "Ashwag", "Ahmad", "Mosaab", "Abdulaziz", "Samer", "Ali", "Mousa", "Mohammed", "Abduallah", "Hamad", "Majed"], "all_groups": [[["Faisal", "Fahad", "Abduallah", "Firas"], ["Ahmad", "Samer", "Ali", "Abdulaziz"], ["Mousa", "Mohammed", "Hatoon", "Salman", "Raghad"], ["Alaa", "Wadia", "Mosaab", "Dania"], ["Ziyad", "Osama", "Naif", "Ashwag", "Sarraa"]], [["Ahmad", "Naif", "Alaa"], ["Mohammed", "Abdulaziz"], ["Abduallah", "Osama", "Mousa"], ["Salman", "Samer", "Wadia"], ["Mosaab", "Raghad", "Ashwag"], ["Hatoon", "Hamad", "Dania"], ["Fahad", "Sarraa", "Ziyad"], ["Ali", "Faisal", "Firas"]], [["Ziyad", "Faisal", "Dania", "Alaa"], ["Abduallah", "Firas", "Naif", "Salman"], ["Ashwag", "Mohammed", "Ali", "Osama"], ["Wadia", "Samer", "Sarraa", "Ahmad"], ["Mosaab", "Hatoon", "Hamad", "Raghad"], ["Mousa", "Abdulaziz", "Fahad"]], [["Osama", "Sarraa"], ["Wadia", "Ahmad"], ["Hamad", "Ziyad"], ["Majed", "Ashwag"], ["Dania", "Mohammed"], ["Abduallah", "Mosaab"], ["Alaa", "Naif"], ["Fahad", "Hatoon"], ["Samer", "Ali"], ["Mousa", "Abdulaziz"], ["Faisal", "Raghad"], ["Salman", "Firas"]]]}